genvm_linter/__init__.py
genvm_linter/cli.py
genvm_linter/linter.py
genvm_linter/type_system.py
genvm_linter/rules/__init__.py
genvm_linter/rules/base.py
genvm_linter/rules/contract.py
genvm_linter/rules/decorators.py
genvm_linter/rules/genvm_dataclasses.py
genvm_linter/rules/genvm_patterns.py
genvm_linter/rules/nondet_storage.py
genvm_linter/rules/python_types.py
genvm_linter/rules/types.py
genvm_linter-0.1.0.dist-info/METADATA
genvm_linter-0.1.0.dist-info/WHEEL
genvm_linter-0.1.0.dist-info/entry_points.txt
genvm_linter-0.1.0.dist-info/RECORD
