Metadata-Version: 2.4
Name: genvm-linter
Version: 0.1.0
Summary: A Python linter for GenLayer GenVM intelligent contracts
Project-URL: Homepage, https://github.com/genlayerlabs/genvm-linter
Project-URL: Repository, https://github.com/genlayerlabs/genvm-linter
Project-URL: Issues, https://github.com/genlayerlabs/genvm-linter/issues
Project-URL: Documentation, https://docs.genlayer.com/developers/intelligent-contracts/tooling-setup
Author-email: GenLayer Labs <dev@genlayer.com>
License-Expression: MIT
Keywords: blockchain,genlayer,genvm,linter,smart-contracts
Classifier: Development Status :: 3 - Alpha
Classifier: Intended Audience :: Developers
Classifier: License :: OSI Approved :: MIT License
Classifier: Programming Language :: Python :: 3
Classifier: Programming Language :: Python :: 3.12
Classifier: Topic :: Software Development :: Quality Assurance
Classifier: Topic :: Software Development :: Testing
Requires-Python: >=3.12
Requires-Dist: click>=8.0.0
Requires-Dist: colorama>=0.4.0
Provides-Extra: dev
Requires-Dist: black>=22.0.0; extra == 'dev'
Requires-Dist: flake8>=5.0.0; extra == 'dev'
Requires-Dist: isort>=5.0.0; extra == 'dev'
Requires-Dist: mypy>=1.0.0; extra == 'dev'
Requires-Dist: pytest-cov>=4.0.0; extra == 'dev'
Requires-Dist: pytest>=7.0.0; extra == 'dev'
